{
  "home": {
    "badge": "AI-powered learning experience",
    "title": "Learn, create and teach with your integrated AI",
    "subtitle": "Hummind allows you to design, deliver and scale personalised learning journeys for schools, bootcamps and organisations.",
    "ctaPrimary": "Get started",
    "ctaSecondary": "Explore the platform",
    "meta": "Built for African schools · Multi-tenant · Secure · Observability powered by PostHog.",

    "spacesTitle": "Workspaces",
    "spacesBadge": "Multi-tenant",
    "open": "Open",

    "spaces": {
      "admin": "Manage institutions, tenants, admins and global platform settings.",
      "auth": "Access login, registration and authentication features.",
      "organisation": "Manage classes, teachers, learners and your organisation’s configuration.",
      "public": "Access the public website, discover features and documentation.",
      "user": "Follow courses, progress through modules and interact with the AI tutor."
    },

    "analyticsTitle": "Product analytics",
    "analyticsDesc": "All clicks and interactions are automatically tracked with PostHog."
  }
}
